<?xml version="1.0" encoding="utf-8" standalone="no"?>
<!DOCTYPE properties SYSTEM "http://java.sun.com/dtd/properties.dtd"[]>
<properties>
  <comment>Elemen-TI JavaPowUpload tatacara fail applet</comment>
  <entry key="Upload.ProgressArea.StatusMessage.Complete">#COMPLETEFILESCOUNT# file upload. Waktu berlalu: #ELAPSEHOUR#: #ELAPSEMIN#: #ELAPSESEC#</entry>
  <entry key="Common.DetailsArea.Thumbnails.ToolTip">Imej melihat / edit</entry>
  <entry key="Common.TopArea.BrowseButton.Label">Layani</entry>
  <entry key="ErrorMessage.FileSizeExceeded">Hanya fail yang besarnya kurang dari #MAXFILESIZE# dibenarkan. #COUNTINVALIDFILES# gambar-gambar yang diabaikan!</entry>
  <entry key="Common.SettingsWindow.ProxyTab.UseProxyLabel">Gunakan proxy</entry>
  <entry key="Common.LoginDialog.DomainLabel">Domain</entry>
  <entry key="Upload.ProgressArea.StatusMessage.NoUploadsInProgress">Jumlah file: #SELECTEDFILESCOUNT# (#TOTALSIZE#).</entry>
  <entry key="Common.ProgressArea.ShowHideLabel.Show">Papar senarai</entry>
  <entry key="ErrorMessage.TotalFileCountExceeded">Hanya #MAXFILECOUNT# file dibenarkan untuk meng-upload! #COUNTINVALIDFILES# gambar-gambar yang diabaikan!</entry>
  <entry key="Common.LoginDialog.Cancel">Membatalkan</entry>
  <entry key="ErrorMessage.UploadUrlEmpty">Parameter Upload.UploadUrl kosong.</entry>
  <entry key="Upload.TopArea.RemoveButton.Label">Padam</entry>
  <entry key="Common.DetailsArea.FileDetails.FileStatus">File status: #FILESTATUS#</entry>
  <entry key="ErrorMessage.HttpError">HTTP kesalahan terjadi. Respons pelayan: #RESPONSE#</entry>
  <entry key="Common.SettingsWindow.ProxyTab.UseBrowserSettings">Gunakan tatacara pelayar</entry>
  <entry key="Upload.TopArea.ClearButton.ToolTip">Padam semua fail dari senarai upload</entry>
  <entry key="Constants.Bytes">bait</entry>
  <entry key="Common.TopArea.BrowseDialog.ApproveButton">OK</entry>
  <entry key="Common.OverwriteDialog.Overwrite">Timpa</entry>
  <entry key="Common.DetailsArea.FileDetails.FolderNameLabel">Folder name: #FOLDERNAME#</entry>
  <entry key="ErrorMessage.CannotCreateFile">Bisa</entry>
  <entry key="Common.RenameDialog.Message">Tentukan nama baru untuk fail #FILENAME#</entry>
  <entry key="Upload.TopArea.RemoveButton.ToolTip">Padam fail yang dipilih dari senarai upload</entry>
  <entry key="Download.TopArea.BrowseButton.ToolTip">Pilih folder tujuan</entry>
  <entry key="Common.LogArea.StatusMessage.FinishFile">[#TIME#] #MODE#: File lengkap #FILENAME#</entry>
  <entry key="Common.DetailsArea.FileDetails.FolderFilesCount">File menghitung: #FILESCOUNT#</entry>
  <entry key="Common.SettingsWindow.ProxyTab.TypeLabel">Jenis:</entry>
  <entry key="Common.LogArea.StatusMessage.Error">[#TIME#] #MODE#: #ERRORMESSAGE#</entry>
  <entry key="Common.SettingsWindow.Caption">Tetapan</entry>
  <entry key="Common.PopupMenu.Remove">Padam</entry>
  <entry key="Upload.ListArea.ToolTip">pohon Gambar membolehkan melihat dan menetapkan fail yang dipilih untuk di-upload</entry>
  <entry key="ErrorMessage.UncompressingFilesizeDoNotMatch">Perhatian mengurai. Filesize tidak sesuai:</entry>
  <entry key="Common.PopupMenu.UncheckAll">Padam tanda semua</entry>
  <entry key="Upload.TopArea.ClearButton.Label">Jelas</entry>
  <entry key="Common.WindowMode.Caption">JavaPowUpload</entry>
  <entry key="ErrorMessage.AddingFileWithJavaScriptInUploadMode">Fail tidak boleh ditambah menggunakan JavaScript di upload mod untuk alasan keselamatan.</entry>
  <entry key="Upload.PopupMenu.UploadSelected">Gambar dipilih</entry>
  <entry key="Download.ProgressArea.StatusMessage.StartingDownloads">Mulai download ...</entry>
  <entry key="Common.PopupMenu.CheckAll">Semak Semua</entry>
  <entry key="Common.PopupMenu.Rename">Tukar nama</entry>
  <entry key="Common.SettingsWindow.MainTab.LanguageLabel">Pilih bahasa</entry>
  <entry key="Common.DetailsArea.DetailView.Columns.Date">Tarikh</entry>
  <entry key="ErrorMessage.ErrorMakingFolder">Kesalahan membuat folder:</entry>
  <entry key="Common.SettingsWindow.ProxyTab.PasswordLabel">Password:</entry>
  <entry key="Common.ProgressArea.StatusMessage.FileComplete">Fail sudah lengkap. Melanjutkan ...</entry>
  <entry key="ErrorMessage.NotValidSSL">Sijil pelayan SSL harus dipercayai atau disahkan. Sila menambah sijil ini ke cantact dipercayai atau dengan pentadbir pelayan.</entry>
  <entry key="Common.SettingsWindow.ProxyTab.SavePasswordLabel">Simpan kata laluan</entry>
  <entry key="Upload.TopArea.BrowseDialog.Title">Pilih fail atau folder</entry>
  <entry key="Common.TopArea.DisplayDetailsButton.Label"></entry>
  <entry key="Common.PopupMenu.Open">Buka</entry>
  <entry key="ErrorMessage.WrongFileType">fail Hanya dengan jenis: #FILETYPES# dibenarkan untuk meng-upload! #COUNTINVALIDFILES# gambar-gambar yang diabaikan!</entry>
  <entry key="ErrorMessage.FtpLibraryNotInstalled">Anda boleh</entry>
  <entry key="Common.DetailsArea.Thumbnails.Cell.RotateLeftIcon.ToolTipText">Putar ke kiri</entry>
  <entry key="Common.SettingsWindow.ProxyTab.DomainLabel">Domain:</entry>
  <entry key="Download.ListArea.Row.Progress.Uncompressing">Uncompressing</entry>
  <entry key="Common.FileStatus.Processing">upload / download dalam penyelesaian</entry>
  <entry key="Common.DetailsArea.FileDetails.FileSizeLabel">File size: #FILESIZE#</entry>
  <entry key="Common.DetailsArea.DetailView.TabName">Details</entry>
  <entry key="Common.ProgressArea.StatusMessage.Waiting">Status: menunggu</entry>
  <entry key="ErrorMessage.TotalFileSizeExceeded">Jumlah fail saiz harus kurang dari #MAXFILESIZETOTAL#. #COUNTINVALIDFILES# gambar-gambar yang diabaikan!</entry>
  <entry key="Download.TopArea.BrowseLabel.Label">Simpan ke:</entry>
  <entry key="Common.DetailsArea.DetailView.Columns.Check">Periksa</entry>
  <entry key="ErrorMessage.NoDataURLSpecified">NO FILE TERTENTU DENGAN INPUT XML</entry>
  <entry key="Common.LoginDialog.Ok">OK</entry>
  <entry key="Upload.ProgressArea.StatusMessage.StartingUploads">Mulai Gambar ..</entry>
  <entry key="Common.OverwriteDialog.SkipAll">Skip semua</entry>
  <entry key="Download.ListArea.Row.Progress.Uncompressed">Terkompresi.</entry>
  <entry key="Common.DetailsArea.Thumbnails.Cell.CropIcon.ToolTipText">Crop gambar</entry>
  <entry key="Common.LogArea.StatusMessage.FtpDownloadMode">Ftp download</entry>
  <entry key="Common.OverwriteDialog.ResumeAll">Teruskan semua</entry>
  <entry key="Common.LoginDialog.Message">Akses ke #FILEURL#</entry>
  <entry key="ErrorMessage.FileSizeMoreThanAllowedRequestSize">Saiz fail lebih dari saiz dibenarkan permintaan.</entry>
  <entry key="Download.ProgressArea.StatusMessage.NoDownloadsInProgress">Jumlah file: #SELECTEDFILESCOUNT# (#TOTALSIZE#).</entry>
  <entry key="Common.DetailsArea.FileDetails.FileDescriptionLabel">Fail Penerangan: #FILEDESCRIPTION#</entry>
  <entry key="Upload.FileSystemTree.TabName">File system</entry>
  <entry key="ErrorMessage.ResponseCode">Respon kod:</entry>
  <entry key="ErrorMessage.OverwritingFile">Timpa</entry>
  <entry key="Common.ListArea.Row.Folder.Label">#FOLDERNAME#</entry>
  <entry key="Common.ProgressArea.StatusMessage.AddingFile">Menambah fail: #FILENAME#</entry>
  <entry key="ErrorMessage.RemoteFilesInUploadMode">file Remote (dengan ftp atau url http) tidak boleh diteruskan dalam mod upload.</entry>
  <entry key="Common.PopupMenu.ProxySettings">Tetapan</entry>
  <entry key="Common.DetailsArea.FileDetails.Caption"></entry>
  <entry key="ErrorMessage.ResponseMessage">Respon mesej:</entry>
  <entry key="ErrorMessage.WrongUploadUrl">Parameter Upload.UploadUrl mempunyai format yang salah (protokol yang sah adalah: ftp, http).</entry>
  <entry key="Download.ProgressArea.DownloadButton.ToolTip">Klik untuk memulakan download</entry>
  <entry key="Common.LoginDialog.LoginLabel">Masuk</entry>
  <entry key="Common.SettingsWindow.MainTab">Utama</entry>
  <entry key="Common.DetailsArea.FileDetails.BackLink">&lt;&lt;Kembali</entry>
  <entry key="Common.ProgressArea.TotalProgress.Text">#TOTALPERCENT#%</entry>
  <entry key="Upload.FileSystemTree.RootName">My Computer</entry>
  <entry key="Upload.ProgressArea.DownloadButton.ToolTip">Klik untuk memulakan upload</entry>
  <entry key="Common.ProgressArea.StatusMessage.CheckConnection">Sambungan usaha: #ATTEMPTNUMBER# (#TIMETOCHECKLEFT# kiri saat). Sambungan dengan pelayan hilang. Menunggu mengembalikan.</entry>
  <entry key="ErrorMessage.FolderAlreadyExists">Folder sudah ada:</entry>
  <entry key="Common.FileStatus.Error">terjadi kesalahan</entry>
  <entry key="Upload.FileFilter.Description.FileSizeLimit">(Saiz fail limit: #MAXFILESIZE#)</entry>
  <entry key="Upload.FileFilter.Description">Dibolehkan fail</entry>
  <entry key="ErrorMessage.OldJREVersionAlert">Berjalan pada jre: #JREVERSION#. Kita perlu jre versi&gt; 1.5.0 untuk memulakan.&lt;br&gt; Anda boleh men-download keluaran terbaru untuk OS anda di sini: http:// java. Com / en / download / manual.jsp</entry>
  <entry key="Common.SettingsWindow.ProxyTab.PortLabel">Port:</entry>
  <entry key="Common.ProgressArea.DownloadButton.StopLabel">Berhenti</entry>
  <entry key="Common.FileStatus.Stopped">berhenti</entry>
  <entry key="ErrorMessage.AccessingFile">Kesalahan mengakses</entry>
  <entry key="Common.DetailsArea.FileDetails.FileNameLabel">File name: #FILENAME#</entry>
  <entry key="Upload.TopArea.BrowseButton.ToolTip">Menambah fail / folder untuk upload</entry>
  <entry key="Common.SettingsWindow.ProxyTab.LoginLabel">Masuk:</entry>
  <entry key="Download.PopupMenu.DownloadSelected">Download dipilih</entry>
  <entry key="Common.FileStatus.Ready">siap untuk diproses</entry>
  <entry key="Common.RenameDialog.Caption">Tukar nama fail #FILENAME#</entry>
  <entry key="Upload.ListArea.RootNodeLabel.Upload">Gambar</entry>
  <entry key="Common.DetailsArea.Thumbnails.TabName">Imej</entry>
  <entry key="Common.LogArea.StatusMessage.FtpUploadMode">Ftp upload</entry>
  <entry key="Common.RenameDialog.Cancel">Membatalkan</entry>
  <entry key="Download.ProgressArea.DownloadButton.Label">Download</entry>
  <entry key="Constants.MegaBytes">MB</entry>
  <entry key="ErrorMessage.ErrorFtpChdir">Tidak boleh menukar (atau) membuat memadam direktori ftp. Respons pelayan:</entry>
  <entry key="Common.LogArea.StatusMessage.HttpUploadMode">Http upload</entry>
  <entry key="Common.PopupMenu.Check">Periksa</entry>
  <entry key="Common.DetailsArea.DetailView.ToolTip">Detil paparan</entry>
  <entry key="Common.RenameDialog.NameLabel">Nama baru</entry>
  <entry key="Common.LoginDialog.PasswordLabel">Password</entry>
  <entry key="Constants.KiloBytes">KB</entry>
  <entry key="Common.OverwriteDialog.Skip">Melewatkan</entry>
  <entry key="Common.LogArea.StatusMessage.StartingFile">[#TIME#] #MODE#: File Bermula #FILENAME#</entry>
  <entry key="ErrorMessage.FtpError">FTP kesalahan terjadi. Respons pelayan: #RESPONSE#</entry>
  <entry key="Download.TopArea.BrowseDialog.Title">Pilih direktori destinasi</entry>
  <entry key="Common.LogArea.StatusMessage.HttpDownloadMode">Http download</entry>
  <entry key="Common.RenameDialog.Ok">OK</entry>
  <entry key="Common.DetailsArea.Thumbnails.Cell.RotateRightIcon.ToolTipText">Putar ke kanan</entry>
  <entry key="Common.ListArea.Row.File.Description.DefaultText">Letakkan fail keterangan di sini</entry>
  <entry key="ErrorMessage.RequestMethod">Permintaan kaedah:</entry>
  <entry key="Common.ProgressArea.StatusMessage.AddingFilesPleaseWait">Menambah fail: berharap tunggu ...</entry>
  <entry key="Upload.FileSystemTree.ToolTip">pohon sistem fail tempatan. Biarkan pilih fail untuk upload</entry>
  <entry key="Common.FileStatus.Complete">lengkap berjaya</entry>
  <entry key="ErrorMessage.WrongFileUrl">Fail tidak disokong url:</entry>
  <entry key="Common.DetailsArea.Thumbnails.Cell.ResetCropIcon.ToolTipText">Undo tanaman operasi</entry>
  <entry key="Upload.ProgressArea.StatusMessage.Uploading">Total: #TOTALPERCENT#% (#FILESNUM#). Lancar: #CURFILEPERCENT#% (#RATEVALUE# / saat, kiri masa: #LEFTHOUR#: #LEFTMIN#: #LEFTSEC#)</entry>
  <entry key="Common.DetailsArea.DetailView.Columns.Path">Path</entry>
  <entry key="ErrorMessage.DownloadedMoreThanFilesize">Didownload lebih dari filesize</entry>
  <entry key="Common.SettingsWindow.ProxyTab">Wakil</entry>
  <entry key="ErrorMessage.CannotMakeHTTPConnection">Tidak boleh membuat Sambungan HTTP ke</entry>
  <entry key="ErrorMessage.HttpClientLibraryNotInstalled">Anda boleh</entry>
  <entry key="Upload.ProgressArea.DownloadButton.Label">Unggah</entry>
  <entry key="Common.DetailsArea.DetailView.Columns.Status">Status</entry>
  <entry key="Common.OverwriteDialog.Message">File #FILENAME# sudah ada. Apa yang anda ingin lakukan?</entry>
  <entry key="Common.LoginDialog.SavePasswordLabel">Simpan kata laluan</entry>
  <entry key="Common.ListArea.Row.File.Label">#FILENAME# [(#FILEPROGRESS#%)]</entry>
  <entry key="ErrorMessage.Uncompressing">Perhatian mengurai</entry>
  <entry key="Common.ProgressArea.StatusMessage.GenerateThumbnail">Hasilkan gambar thumbnail #FILENAME#</entry>
  <entry key="Common.DetailsArea.FileDetails.FilePathLabel">#FILEPATH#</entry>
  <entry key="Common.LoginDialog.Caption">Masuk ke #HOST#</entry>
  <entry key="Common.PopupMenu.Uncheck">Padam tanda</entry>
  <entry key="ErrorMessage.CannotMakeFTPConnection">Tidak boleh membuat sambungan FTP untuk #HOST#. Perhatian: #ERROR#. Respons pelayan: #RESPONSE#</entry>
  <entry key="Common.PopupMenu.AddFolder">Tambah folder untuk meng-upload</entry>
  <entry key="Download.ListArea.RootNodeLabel.Download">Downloads</entry>
  <entry key="Common.DetailsArea.FileDetails.FolderSizeLabel">Folder Saiz: #FOLDERSIZE#</entry>
  <entry key="Download.ProgressArea.StatusMessage.Complete">#COMPLETEFILESCOUNT# fail yang didownload. Waktu berlalu: #ELAPSEHOUR#: #ELAPSEMIN#: #ELAPSESEC#</entry>
  <entry key="Common.DetailsArea.DetailView.Columns.Size">Saiz</entry>
  <entry key="Common.ListArea.Row.File.ErrorLabel">&lt;html&gt; &lt;font style="font-weight: bold; color:#FF0000" &gt; Perhatian: #ERRORMESSAGE# &lt;/font&gt; &lt;/html&gt;</entry>
  <entry key="Constants.GigaBytes">GB</entry>
  <entry key="Common.OverwriteDialog.OverwriteAll">Menimpa semua</entry>
  <entry key="Common.DetailsArea.DetailView.Columns.Thumbnail">Imej</entry>
  <entry key="Download.ProgressArea.StatusMessage.Downloading">Total: #TOTALPERCENT#% (#FILESNUM#). Lancar: #CURFILEPERCENT#% (#RATEVALUE# / saat, kiri masa: #LEFTHOUR#: #LEFTMIN#: #LEFTSEC#)</entry>
  <entry key="ErrorMessage.AppletNotSigned">Applet tidak SIGNED, ATAU PENGGUNA TIDAK MENERIMA TANDA TANGAN</entry>
  <entry key="Common.SettingsWindow.ProxyTab.HostLabel">Host:</entry>
  <entry key="Common.DetailsArea.DetailView.Columns.Name">Nama</entry>
  <entry key="Common.ListArea.Row.Progress.Downloading">#CURFILEPERCENT#%</entry>
  <entry key="Common.TopArea.DisplayDetailsButton.ToolTip">Papar / Maklum butiran panel</entry>
  <entry key="Common.ListArea.TabName">Gambar pohon</entry>
  <entry key="Common.OverwriteDialog.Resume">Resume</entry>
  <entry key="Common.DetailsArea.FileDetails.FileLastModifiedLabel">Fail diubah buat kali terakhir: #FILEDATE#</entry>
  <entry key="ErrorMessage.LocalFilesInDownloadMode">Tempatan fail boleh</entry>
</properties>